LICENSE.md
MANIFEST.in
README.md
ghtix.py
setup.py
template.ghtix.json
ghtix.egg-info/PKG-INFO
ghtix.egg-info/SOURCES.txt
ghtix.egg-info/dependency_links.txt
ghtix.egg-info/requires.txt
ghtix.egg-info/top_level.txt
github_apiv3/__init__.py
github_apiv3/client.py
github_apiv3/request.py