Metadata-Version: 1.1
Name: ghtix
Version: 0.1.7
Summary: A simple tool to summarize github issues across projects
Home-page: http://github.com/perrygeo/ghtix
Author: Matthew Perry
Author-email: perrygeo@gmail.com
License: New BSD License
Keywords: tickets issues tracker github project management
Platform: UNKNOWN
Classifier: License :: OSI Approved :: BSD License
Classifier: Operating System :: OS Independent
Classifier: Programming Language :: Python
Classifier: Environment :: Console
